http_benchmark/__init__.py
http_benchmark/benchmark.py
http_benchmark/cli.py
http_benchmark/storage.py
http_benchmark/clients/__init__.py
http_benchmark/clients/aiohttp_adapter.py
http_benchmark/clients/base.py
http_benchmark/clients/httpx_adapter.py
http_benchmark/clients/pycurl_adapter.py
http_benchmark/clients/requests_adapter.py
http_benchmark/clients/requestx_adapter.py
http_benchmark/clients/urllib3_adapter.py
http_benchmark/models/__init__.py
http_benchmark/models/base.py
http_benchmark/models/benchmark_configuration.py
http_benchmark/models/benchmark_result.py
http_benchmark/models/http_request.py
http_benchmark/models/resource_metrics.py
http_benchmark/utils/__init__.py
http_benchmark/utils/logging.py
http_benchmark/utils/resource_monitor.py
http_client_benchmarker-5.0.1.dist-info/METADATA
http_client_benchmarker-5.0.1.dist-info/WHEEL
http_client_benchmarker-5.0.1.dist-info/entry_points.txt
http_client_benchmarker-5.0.1.dist-info/top_level.txt
http_client_benchmarker-5.0.1.dist-info/RECORD
