Metadata-Version: 2.4
Name: http-client-benchmarker
Version: 5.0.1
Summary: A Python HTTP Client Performance Benchmark Framework
Author-email: Qunfei Wu <wu.qunfei@gmail.com>
License: MIT
Classifier: Development Status :: 3 - Alpha
Classifier: Intended Audience :: Developers
Classifier: License :: OSI Approved :: MIT License
Classifier: Programming Language :: Python :: 3
Classifier: Programming Language :: Python :: 3.12
Requires-Python: >=3.12
Requires-Dist: requests>=2.31.0
Requires-Dist: requestx>=0.1.0
Requires-Dist: httpx>=0.27.0
Requires-Dist: aiohttp>=3.9.0
Requires-Dist: urllib3>=2.0.0
Requires-Dist: pycurl>=7.45.0
Requires-Dist: loguru>=0.7.0
Requires-Dist: psutil>=5.9.0
Requires-Dist: twine>=6.2.0
Provides-Extra: dev
Requires-Dist: pytest>=7.0; extra == "dev"
Requires-Dist: pytest-asyncio>=0.21; extra == "dev"
Requires-Dist: black>=23.0; extra == "dev"
Requires-Dist: flake8>=6.0; extra == "dev"
Requires-Dist: mypy>=1.0; extra == "dev"
